spacy_universal_sentence_encoder/__init__.py
spacy_universal_sentence_encoder/language.py
spacy_universal_sentence_encoder/util.py
spacy_universal_sentence_encoder/meta/en_use_lg.json
spacy_universal_sentence_encoder/meta/en_use_md.json
spacy_universal_sentence_encoder/meta/xx_use_lg.json
spacy_universal_sentence_encoder/meta/xx_use_md.json
spacy_universal_sentence_encoder-0.2.1.dist-info/LICENSE
spacy_universal_sentence_encoder-0.2.1.dist-info/METADATA
spacy_universal_sentence_encoder-0.2.1.dist-info/WHEEL
spacy_universal_sentence_encoder-0.2.1.dist-info/entry_points.txt
spacy_universal_sentence_encoder-0.2.1.dist-info/top_level.txt
spacy_universal_sentence_encoder-0.2.1.dist-info/RECORD
