Metadata-Version: 2.1
Name: spacy-universal-sentence-encoder
Version: 0.2.1
Summary: SpaCy models for using Universal Sentence Encoder from TensorFlow Hub
Home-page: https://github.com/MartinoMensio/spacy-universal-sentence-encoder-tfhub
Author: Martino Mensio
Author-email: martino.mensio@open.ac.uk
License: UNKNOWN
Platform: UNKNOWN
Requires-Dist: tensorflow (==2.1.0)
Requires-Dist: tensorflow-text (==2.1.1)
Requires-Dist: spacy
Requires-Dist: tensorflow-hub
